{
	"type" : "recipe",
	"work_units" : 4,
	"recipe_name" : "i18n(homesweethome:jobs.potter.recipes.crockery_recipe.recipe_name)",
	"description" : "i18n(homesweethome:jobs.potter.recipes.crockery_recipe.description)",
	"flavor" : "i18n(homesweethome:jobs.potter.recipes.crockery_recipe.flavor)",
	"portrait" : "/homesweethome/entities/decoration/crockery_rayya/crockery_rayya.png",
	"level_requirement" : 1,
	"workshop" : "stonehearth:potter:workbench",
	"manual_unlock": true,
	"ingredients" : [
		{
			"material": "clay resource",
			"count" : 3
		}
	],
	"produces" : [
		{
			"item" : "homesweethome:decoration:potter_crockery_rayya"
		}
	]
}
